GNSS_Vel_95CI/GNSS_Vel_95CI.py
GNSS_Vel_95CI/__init__.py
GNSS_Vel_95CI-1.0.8.dist-info/LICENSE
GNSS_Vel_95CI-1.0.8.dist-info/METADATA
GNSS_Vel_95CI-1.0.8.dist-info/WHEEL
GNSS_Vel_95CI-1.0.8.dist-info/top_level.txt
GNSS_Vel_95CI-1.0.8.dist-info/RECORD
