Metadata-Version: 2.1
Name: GNSS-Vel-95CI
Version: 1.0.8
Summary: A Python program for calculating the 95 percent CI for GNSS derived site velocities
Home-page: https://github.com/bob-Github-2020
Author: Brendan Cornelison,Guoquan Wang
Author-email: bscornelison@gmail.com,gwang@uh.edu
Classifier: Programming Language :: Python :: 3
Classifier: License :: OSI Approved :: MIT License
Classifier: Operating System :: OS Independent
Requires-Python: >=3.6
License-File: LICENSE
